felarc/__init__.py
felarc/analysis.py
felarc/constants.py
felarc/family.py
felarc/maps.py
felarc/matching.py
felarc/maths.py
felarc/plot.py
felarc/py.typed
felarc/simple_tba.py
felarc/t20.py
felarc/tba.py
felarc/test.py
felarc/tracking.py
felarc/utils.py
felarc-0.2.0.dist-info/METADATA
felarc-0.2.0.dist-info/WHEEL
felarc-0.2.0.dist-info/RECORD
