Metadata-Version: 2.4
Name: felarc
Version: 0.2.0
Summary: Add your description here
Requires-Python: >=3.12
Requires-Dist: latdraw>=0.1.1a3
Requires-Dist: matplotlib>=3.10.3
Requires-Dist: ocelot-desy>=25.6.0
Requires-Dist: sympy>=1.14.0
Requires-Dist: tabulate>=0.9.0
